wcloud/__init__.py
wcloud/cli.py
wcloud/wcloud.py
wcloud-0.1.0.dist-info/DESCRIPTION.rst
wcloud-0.1.0.dist-info/entry_points.txt
wcloud-0.1.0.dist-info/METADATA
wcloud-0.1.0.dist-info/metadata.json
wcloud-0.1.0.dist-info/RECORD
wcloud-0.1.0.dist-info/top_level.txt
wcloud-0.1.0.dist-info/WHEEL
