Metadata-Version: 2.0
Name: wcloud
Version: 0.1.0
Summary: Command line tool to generate wordclouds.
Home-page: https://github.com/neocortex/wcloud
Author: Rafael Schultze-Kraft
Author-email: skraftr@gmail.com
License: MIT license
Keywords: wcloud
Platform: UNKNOWN
Classifier: Development Status :: 3 - Alpha
Classifier: Intended Audience :: Developers
Classifier: License :: OSI Approved :: MIT License
Classifier: Natural Language :: English
Classifier: Programming Language :: Python :: 2
Classifier: Programming Language :: Python :: 2.7
Classifier: Programming Language :: Python :: 3
Classifier: Programming Language :: Python :: 3.3
Classifier: Programming Language :: Python :: 3.4
Classifier: Programming Language :: Python :: 3.5
Requires-Dist: Click (>=6.0)
Requires-Dist: Pillow (==3.3.0)
Requires-Dist: numpy (==1.11.1)
Requires-Dist: wordcloud (==1.2.1)
